README.rst
setup.py
pyfav2/__init__.py
pyfav2/pyfav2.py
pyfav2.egg-info/PKG-INFO
pyfav2.egg-info/SOURCES.txt
pyfav2.egg-info/dependency_links.txt
pyfav2.egg-info/requires.txt
pyfav2.egg-info/top_level.txt
test/__init__.py
test/pyfav_test.py